[
  {
    "name": "Application Start",
    "start": 1597985953168,
    "end": 1597985954259,
    "duration": 1091,
    "pid": 13488,
    "index": 0
  },
  {
    "name": "Load Plugin",
    "start": 1597985953175,
    "end": 1597985953197,
    "duration": 22,
    "pid": 13488,
    "index": 1
  },
  {
    "name": "Load Config",
    "start": 1597985953198,
    "end": 1597985953238,
    "duration": 40,
    "pid": 13488,
    "index": 2
  },
  {
    "name": "Require(0) config/config.default.js",
    "start": 1597985953199,
    "end": 1597985953199,
    "duration": 0,
    "pid": 13488,
    "index": 3
  },
  {
    "name": "Require(1) node_modules/egg-session/config/config.default.js",
    "start": 1597985953202,
    "end": 1597985953203,
    "duration": 1,
    "pid": 13488,
    "index": 4
  },
  {
    "name": "Require(2) node_modules/egg-security/config/config.default.js",
    "start": 1597985953204,
    "end": 1597985953204,
    "duration": 0,
    "pid": 13488,
    "index": 5
  },
  {
    "name": "Require(3) node_modules/egg-jsonp/config/config.default.js",
    "start": 1597985953206,
    "end": 1597985953207,
    "duration": 1,
    "pid": 13488,
    "index": 6
  },
  {
    "name": "Require(4) node_modules/egg-onerror/config/config.default.js",
    "start": 1597985953208,
    "end": 1597985953208,
    "duration": 0,
    "pid": 13488,
    "index": 7
  },
  {
    "name": "Require(5) node_modules/egg-i18n/config/config.default.js",
    "start": 1597985953209,
    "end": 1597985953209,
    "duration": 0,
    "pid": 13488,
    "index": 8
  },
  {
    "name": "Require(6) node_modules/egg-watcher/config/config.default.js",
    "start": 1597985953211,
    "end": 1597985953212,
    "duration": 1,
    "pid": 13488,
    "index": 9
  },
  {
    "name": "Require(7) node_modules/egg-schedule/config/config.default.js",
    "start": 1597985953212,
    "end": 1597985953213,
    "duration": 1,
    "pid": 13488,
    "index": 10
  },
  {
    "name": "Require(8) node_modules/egg-multipart/config/config.default.js",
    "start": 1597985953214,
    "end": 1597985953214,
    "duration": 0,
    "pid": 13488,
    "index": 11
  },
  {
    "name": "Require(9) node_modules/egg-development/config/config.default.js",
    "start": 1597985953216,
    "end": 1597985953216,
    "duration": 0,
    "pid": 13488,
    "index": 12
  },
  {
    "name": "Require(10) node_modules/egg-logrotator/config/config.default.js",
    "start": 1597985953217,
    "end": 1597985953218,
    "duration": 1,
    "pid": 13488,
    "index": 13
  },
  {
    "name": "Require(11) node_modules/egg-static/config/config.default.js",
    "start": 1597985953219,
    "end": 1597985953219,
    "duration": 0,
    "pid": 13488,
    "index": 14
  },
  {
    "name": "Require(12) node_modules/egg-view/config/config.default.js",
    "start": 1597985953220,
    "end": 1597985953221,
    "duration": 1,
    "pid": 13488,
    "index": 15
  },
  {
    "name": "Require(13) node_modules/egg-cors/config/config.default.js",
    "start": 1597985953222,
    "end": 1597985953222,
    "duration": 0,
    "pid": 13488,
    "index": 16
  },
  {
    "name": "Require(14) node_modules/egg-validate/config/config.default.js",
    "start": 1597985953223,
    "end": 1597985953223,
    "duration": 0,
    "pid": 13488,
    "index": 17
  },
  {
    "name": "Require(15) node_modules/egg-email/config/config.default.js",
    "start": 1597985953224,
    "end": 1597985953224,
    "duration": 0,
    "pid": 13488,
    "index": 18
  },
  {
    "name": "Require(16) node_modules/egg/config/config.default.js",
    "start": 1597985953225,
    "end": 1597985953226,
    "duration": 1,
    "pid": 13488,
    "index": 19
  },
  {
    "name": "Require(17) config/config.default.js",
    "start": 1597985953230,
    "end": 1597985953230,
    "duration": 0,
    "pid": 13488,
    "index": 20
  },
  {
    "name": "Require(18) node_modules/egg-security/config/config.local.js",
    "start": 1597985953231,
    "end": 1597985953232,
    "duration": 1,
    "pid": 13488,
    "index": 21
  },
  {
    "name": "Require(19) node_modules/egg-watcher/config/config.local.js",
    "start": 1597985953233,
    "end": 1597985953234,
    "duration": 1,
    "pid": 13488,
    "index": 22
  },
  {
    "name": "Require(20) node_modules/egg-view/config/config.local.js",
    "start": 1597985953235,
    "end": 1597985953236,
    "duration": 1,
    "pid": 13488,
    "index": 23
  },
  {
    "name": "Require(21) node_modules/egg/config/config.local.js",
    "start": 1597985953237,
    "end": 1597985953238,
    "duration": 1,
    "pid": 13488,
    "index": 24
  },
  {
    "name": "Load extend/application.js",
    "start": 1597985953241,
    "end": 1597985953259,
    "duration": 18,
    "pid": 13488,
    "index": 25
  },
  {
    "name": "Require(22) node_modules/egg-session/app/extend/application.js",
    "start": 1597985953242,
    "end": 1597985953243,
    "duration": 1,
    "pid": 13488,
    "index": 26
  },
  {
    "name": "Require(23) node_modules/egg-security/app/extend/application.js",
    "start": 1597985953243,
    "end": 1597985953245,
    "duration": 2,
    "pid": 13488,
    "index": 27
  },
  {
    "name": "Require(24) node_modules/egg-jsonp/app/extend/application.js",
    "start": 1597985953246,
    "end": 1597985953247,
    "duration": 1,
    "pid": 13488,
    "index": 28
  },
  {
    "name": "Require(25) node_modules/egg-logrotator/app/extend/application.js",
    "start": 1597985953249,
    "end": 1597985953251,
    "duration": 2,
    "pid": 13488,
    "index": 29
  },
  {
    "name": "Require(26) node_modules/egg-view/app/extend/application.js",
    "start": 1597985953251,
    "end": 1597985953253,
    "duration": 2,
    "pid": 13488,
    "index": 30
  },
  {
    "name": "Load extend/request.js",
    "start": 1597985953259,
    "end": 1597985953270,
    "duration": 11,
    "pid": 13488,
    "index": 31
  },
  {
    "name": "Require(27) node_modules/egg/app/extend/request.js",
    "start": 1597985953263,
    "end": 1597985953266,
    "duration": 3,
    "pid": 13488,
    "index": 32
  },
  {
    "name": "Load extend/response.js",
    "start": 1597985953270,
    "end": 1597985953279,
    "duration": 9,
    "pid": 13488,
    "index": 33
  },
  {
    "name": "Require(28) node_modules/egg/app/extend/response.js",
    "start": 1597985953274,
    "end": 1597985953276,
    "duration": 2,
    "pid": 13488,
    "index": 34
  },
  {
    "name": "Load extend/context.js",
    "start": 1597985953279,
    "end": 1597985953402,
    "duration": 123,
    "pid": 13488,
    "index": 35
  },
  {
    "name": "Require(29) node_modules/egg-security/app/extend/context.js",
    "start": 1597985953279,
    "end": 1597985953291,
    "duration": 12,
    "pid": 13488,
    "index": 36
  },
  {
    "name": "Require(30) node_modules/egg-jsonp/app/extend/context.js",
    "start": 1597985953292,
    "end": 1597985953293,
    "duration": 1,
    "pid": 13488,
    "index": 37
  },
  {
    "name": "Require(31) node_modules/egg-i18n/app/extend/context.js",
    "start": 1597985953294,
    "end": 1597985953295,
    "duration": 1,
    "pid": 13488,
    "index": 38
  },
  {
    "name": "Require(32) node_modules/egg-multipart/app/extend/context.js",
    "start": 1597985953295,
    "end": 1597985953389,
    "duration": 94,
    "pid": 13488,
    "index": 39
  },
  {
    "name": "Require(33) node_modules/egg-view/app/extend/context.js",
    "start": 1597985953393,
    "end": 1597985953394,
    "duration": 1,
    "pid": 13488,
    "index": 40
  },
  {
    "name": "Require(34) node_modules/egg-validate/app/extend/context.js",
    "start": 1597985953395,
    "end": 1597985953396,
    "duration": 1,
    "pid": 13488,
    "index": 41
  },
  {
    "name": "Require(35) node_modules/egg/app/extend/context.js",
    "start": 1597985953397,
    "end": 1597985953400,
    "duration": 3,
    "pid": 13488,
    "index": 42
  },
  {
    "name": "Load extend/helper.js",
    "start": 1597985953402,
    "end": 1597985953434,
    "duration": 32,
    "pid": 13488,
    "index": 43
  },
  {
    "name": "Require(36) node_modules/egg-security/app/extend/helper.js",
    "start": 1597985953403,
    "end": 1597985953427,
    "duration": 24,
    "pid": 13488,
    "index": 44
  },
  {
    "name": "Require(37) node_modules/egg/app/extend/helper.js",
    "start": 1597985953429,
    "end": 1597985953429,
    "duration": 0,
    "pid": 13488,
    "index": 45
  },
  {
    "name": "Require(38) app/extend/helper.js",
    "start": 1597985953430,
    "end": 1597985953430,
    "duration": 0,
    "pid": 13488,
    "index": 46
  },
  {
    "name": "Load app.js",
    "start": 1597985953435,
    "end": 1597985953575,
    "duration": 140,
    "pid": 13488,
    "index": 47
  },
  {
    "name": "Require(39) node_modules/egg-session/app.js",
    "start": 1597985953435,
    "end": 1597985953435,
    "duration": 0,
    "pid": 13488,
    "index": 48
  },
  {
    "name": "Require(40) node_modules/egg-security/app.js",
    "start": 1597985953436,
    "end": 1597985953438,
    "duration": 2,
    "pid": 13488,
    "index": 49
  },
  {
    "name": "Require(41) node_modules/egg-onerror/app.js",
    "start": 1597985953439,
    "end": 1597985953452,
    "duration": 13,
    "pid": 13488,
    "index": 50
  },
  {
    "name": "Require(42) node_modules/egg-i18n/app.js",
    "start": 1597985953453,
    "end": 1597985953475,
    "duration": 22,
    "pid": 13488,
    "index": 51
  },
  {
    "name": "Require(43) node_modules/egg-watcher/app.js",
    "start": 1597985953476,
    "end": 1597985953480,
    "duration": 4,
    "pid": 13488,
    "index": 52
  },
  {
    "name": "Require(44) node_modules/egg-schedule/app.js",
    "start": 1597985953481,
    "end": 1597985953482,
    "duration": 1,
    "pid": 13488,
    "index": 53
  },
  {
    "name": "Require(45) node_modules/egg-multipart/app.js",
    "start": 1597985953483,
    "end": 1597985953486,
    "duration": 3,
    "pid": 13488,
    "index": 54
  },
  {
    "name": "Require(46) node_modules/egg-development/app.js",
    "start": 1597985953487,
    "end": 1597985953488,
    "duration": 1,
    "pid": 13488,
    "index": 55
  },
  {
    "name": "Require(47) node_modules/egg-logrotator/app.js",
    "start": 1597985953488,
    "end": 1597985953489,
    "duration": 1,
    "pid": 13488,
    "index": 56
  },
  {
    "name": "Require(48) node_modules/egg-static/app.js",
    "start": 1597985953489,
    "end": 1597985953490,
    "duration": 1,
    "pid": 13488,
    "index": 57
  },
  {
    "name": "Require(49) node_modules/egg-cors/app.js",
    "start": 1597985953491,
    "end": 1597985953491,
    "duration": 0,
    "pid": 13488,
    "index": 58
  },
  {
    "name": "Require(50) node_modules/egg-validate/app.js",
    "start": 1597985953492,
    "end": 1597985953496,
    "duration": 4,
    "pid": 13488,
    "index": 59
  },
  {
    "name": "Require(51) node_modules/egg-email/app.js",
    "start": 1597985953496,
    "end": 1597985953573,
    "duration": 77,
    "pid": 13488,
    "index": 60
  },
  {
    "name": "Before Start in node_modules/egg-watcher/lib/init.js:15:14",
    "start": 1597985953603,
    "end": 1597985954256,
    "duration": 653,
    "pid": 13488,
    "index": 61
  },
  {
    "name": "Load Service",
    "start": 1597985953662,
    "end": 1597985953693,
    "duration": 31,
    "pid": 13488,
    "index": 62
  },
  {
    "name": "Load \"service\" to Context",
    "start": 1597985953662,
    "end": 1597985953693,
    "duration": 31,
    "pid": 13488,
    "index": 63
  },
  {
    "name": "Load Middleware",
    "start": 1597985953693,
    "end": 1597985953823,
    "duration": 130,
    "pid": 13488,
    "index": 64
  },
  {
    "name": "Load \"middlewares\" to Application",
    "start": 1597985953693,
    "end": 1597985953805,
    "duration": 112,
    "pid": 13488,
    "index": 65
  },
  {
    "name": "Load Controller",
    "start": 1597985953823,
    "end": 1597985954177,
    "duration": 354,
    "pid": 13488,
    "index": 66
  },
  {
    "name": "Load \"controller\" to Application",
    "start": 1597985953823,
    "end": 1597985954177,
    "duration": 354,
    "pid": 13488,
    "index": 67
  },
  {
    "name": "Load Router",
    "start": 1597985954178,
    "end": 1597985954182,
    "duration": 4,
    "pid": 13488,
    "index": 68
  },
  {
    "name": "Require(52) app/router.js",
    "start": 1597985954178,
    "end": 1597985954178,
    "duration": 0,
    "pid": 13488,
    "index": 69
  },
  {
    "name": "Before Start in node_modules/egg-core/lib/egg.js:303:10",
    "start": 1597985954179,
    "end": 1597985954197,
    "duration": 18,
    "pid": 13488,
    "index": 70
  }
]